jtssql/__init__.py
jtssql/table.py
jtssql/util.py
jtssql-0.1.dist-info/DESCRIPTION.rst
jtssql-0.1.dist-info/METADATA
jtssql-0.1.dist-info/metadata.json
jtssql-0.1.dist-info/namespace_packages.txt
jtssql-0.1.dist-info/RECORD
jtssql-0.1.dist-info/top_level.txt
jtssql-0.1.dist-info/WHEEL
tests/__init__.py
tests/test_table.py
tests/util.py
