Metadata-Version: 2.0
Name: jtssql
Version: 0.1
Summary: Generate database tables based on JSON Table Schema
Home-page: http://github.com/okfn/jtssql
Author: Friedrich Lindenberg
Author-email: friedrich@pudo.org
License: MIT
Keywords: schema jsontableschema jts sql data
Platform: UNKNOWN
Classifier: Development Status :: 3 - Alpha
Classifier: Intended Audience :: Developers
Classifier: License :: OSI Approved :: MIT License
Classifier: Operating System :: OS Independent
Classifier: Programming Language :: Python :: 2.6
Classifier: Programming Language :: Python :: 2.7
Classifier: Programming Language :: Python :: 3.3
Classifier: Programming Language :: Python :: 3.4
Requires-Dist: sqlalchemy (>=1.0)
Requires-Dist: typecast (>=0.2.2)
Requires-Dist: normality
